mochi_re/__init__.py
mochi_re/cli.py
mochi_re/highlighters/__init__.py
mochi_re/highlighters/pattern_highlight.py
mochi_re/logic/Debouncer.py
mochi_re/logic/GlobalState.py
mochi_re/logic/RegexLogic.py
mochi_re/logic/__init__.py
mochi_re/metaclasses/__init__.py
mochi_re/metaclasses/singelton.py
mochi_re/mochi.py
mochi_re/screens/Help/Help.py
mochi_re/screens/Help/HelpScreen.tcss
mochi_re/screens/Help/__init__.py
mochi_re/screens/Home/Home.py
mochi_re/screens/Home/Home.tcss
mochi_re/screens/Home/__init__.py
mochi_re/screens/RegexModes/RegexModes.py
mochi_re/screens/RegexModes/RegexModes.tcss
mochi_re/screens/RegexModes/__init__.py
mochi_re/screens/RegexOptions/RegexOptions.py
mochi_re/screens/RegexOptions/RegexOptions.tcss
mochi_re/screens/RegexOptions/__init__.py
mochi_re/screens/__init__.py
mochi_re/widgets/__init__.py
mochi_re/widgets/inputs/CmdInput/CmdInput.py
mochi_re/widgets/inputs/CmdInput/__init__.py
mochi_re/widgets/inputs/ColoredInputArea/ColoredInputArea.py
mochi_re/widgets/inputs/ColoredInputArea/__init__.py
mochi_re/widgets/inputs/PatternInput/PatternInput.py
mochi_re/widgets/inputs/PatternInput/__init__.py
mochi_re/widgets/inputs/SubstitutionInput/SubstitutionInput.py
mochi_re/widgets/inputs/SubstitutionInput/__init__.py
mochi_re/widgets/inputs/SubstitutionInputArea/SubstitutionInputArea.py
mochi_re/widgets/inputs/SubstitutionInputArea/__init__.py
mochi_re/widgets/inputs/__init__.py
mochi_re/widgets/labels/Logo/Logo.py
mochi_re/widgets/labels/Logo/__init__.py
mochi_re/widgets/labels/__init__.py
mochi_re/widgets/widgets/CustomHeader/CustomHeader.py
mochi_re/widgets/widgets/CustomHeader/__init__.py
mochi_re/widgets/widgets/FooterMode/FooterMode.py
mochi_re/widgets/widgets/FooterMode/__init__.py
mochi_re/widgets/widgets/FooterOptions/FooterOptions.py
mochi_re/widgets/widgets/FooterOptions/__init__.py
mochi_re/widgets/widgets/GeneralData/GeneralData.py
mochi_re/widgets/widgets/GeneralData/__init__.py
mochi_re/widgets/widgets/GroupsArea/GroupsArea.py
mochi_re-0.2.5.dist-info/LICENSE
mochi_re-0.2.5.dist-info/METADATA
mochi_re-0.2.5.dist-info/WHEEL
mochi_re-0.2.5.dist-info/entry_points.txt
mochi_re-0.2.5.dist-info/RECORD
